the_toob/Constant.py
the_toob/ToobBrowser.py
the_toob/Uploader.py
the_toob/UploaderPage.py
the_toob/__init__.py
the_toob/__main__.py
the_toob-1.0.0.dist-info/licenses/LICENSE
the_toob-1.0.0.dist-info/METADATA
the_toob-1.0.0.dist-info/WHEEL
the_toob-1.0.0.dist-info/entry_points.txt
the_toob-1.0.0.dist-info/top_level.txt
the_toob-1.0.0.dist-info/RECORD
