Metadata-Version: 2.4
Name: the-toob
Version: 1.0.0
Summary: A modern interface for automating a browser to upload videos to YouTube.
Author-email: "JW Drummond (MD Wade)" <wade@mdwade.com>
License: MIT
Project-URL: Homepage, https://github.com/MD-Wade/the-toob
Project-URL: Issues, https://github.com/MD-Wade/the-toob/issues
Classifier: Development Status :: 5 - Production/Stable
Classifier: License :: OSI Approved :: MIT License
Classifier: Intended Audience :: Developers
Classifier: Topic :: Internet :: WWW/HTTP
Classifier: Topic :: Multimedia :: Video
Classifier: Programming Language :: Python :: 3
Classifier: Programming Language :: Python :: 3.8
Classifier: Programming Language :: Python :: 3.9
Classifier: Programming Language :: Python :: 3.10
Classifier: Programming Language :: Python :: 3.11
Classifier: Programming Language :: Python :: 3.12
Classifier: Operating System :: OS Independent
Requires-Python: >=3.8
License-File: LICENSE
Requires-Dist: selenium>=4.6.0
Dynamic: license-file
